sqlalchemy_lightening/__init__.py
sqlalchemy_lightening/association.py
sqlalchemy_lightening/query.py
sqlalchemy_lightening/relationship.py
sqlalchemy_lightening/result_list.py
sqlalchemy_lightening-0.6.0.dist-info/LICENSE.txt
sqlalchemy_lightening-0.6.0.dist-info/METADATA
sqlalchemy_lightening-0.6.0.dist-info/WHEEL
sqlalchemy_lightening-0.6.0.dist-info/top_level.txt
sqlalchemy_lightening-0.6.0.dist-info/RECORD
