Metadata-Version: 2.1
Name: sqlalchemy-lightening
Version: 0.6.0
Summary: making SQLAlchemy great again
Home-page: https://github.com/dpep/py_sqlalchemy_lightening
Author: Daniel Pepper
License: MIT
Platform: any
Classifier: License :: OSI Approved :: MIT License
Classifier: Programming Language :: Python
Classifier: Topic :: Utilities
License-File: LICENSE.txt
Requires-Dist: classproperties (>=0.2)
Requires-Dist: pluckit (>=0.6)
Requires-Dist: rekey (>=1.2)
Requires-Dist: sqlalchemy (<1.4,>=1.2.18)
Requires-Dist: stringcase (>=1.2)
